diagnnose/__init__.py
diagnnose/pipeline.py
diagnnose/activations/__init__.py
diagnnose/activations/activation_index.py
diagnnose/activations/activation_reader.py
diagnnose/activations/activation_writer.py
diagnnose/activations/selection_funcs.py
diagnnose/attribute/__init__.py
diagnnose/attribute/decomposer.py
diagnnose/attribute/explainer.py
diagnnose/attribute/gcd_tensor.py
diagnnose/attribute/shapley_tensor.py
diagnnose/attribute/utils.py
diagnnose/config/__init__.py
diagnnose/config/arg_descriptions.py
diagnnose/config/config_dict.py
diagnnose/corpus/__init__.py
diagnnose/corpus/corpus.py
diagnnose/corpus/create_iterator.py
diagnnose/corpus/create_labels.py
diagnnose/extract/__init__.py
diagnnose/extract/extractor.py
diagnnose/extract/simple_extract.py
diagnnose/models/__init__.py
diagnnose/models/import_model.py
diagnnose/models/init_states.py
diagnnose/models/language_model.py
diagnnose/models/recurrent_lm.py
diagnnose/models/transformer_lm.py
diagnnose/models/wrappers/__init__.py
diagnnose/models/wrappers/awd_lstm.py
diagnnose/models/wrappers/forward_lstm.py
diagnnose/models/wrappers/google_lm.py
diagnnose/probe/__init__.py
diagnnose/probe/data_loader.py
diagnnose/probe/dc_trainer.py
diagnnose/probe/logreg.py
diagnnose/syntax/__init__.py
diagnnose/syntax/evaluator.py
diagnnose/syntax/task.py
diagnnose/syntax/tasks/__init__.py
diagnnose/syntax/tasks/lakretz.py
diagnnose/syntax/tasks/linzen.py
diagnnose/syntax/tasks/marvin.py
diagnnose/syntax/tasks/warstadt.py
diagnnose/syntax/tasks/warstadt_preproc.py
diagnnose/syntax/tasks/winobias.py
diagnnose/tokenizer/__init__.py
diagnnose/tokenizer/c2i.py
diagnnose/tokenizer/create.py
diagnnose/tokenizer/w2i.py
diagnnose/typedefs/__init__.py
diagnnose/typedefs/activations.py
diagnnose/typedefs/probe.py
diagnnose/typedefs/syntax.py
diagnnose/utils/__init__.py
diagnnose/utils/misc.py
diagnnose/utils/pickle.py
diagNNose-1.1.dist-info/LICENSE
diagNNose-1.1.dist-info/METADATA
diagNNose-1.1.dist-info/WHEEL
diagNNose-1.1.dist-info/top_level.txt
diagNNose-1.1.dist-info/RECORD
