Metadata-Version: 2.1
Name: diagNNose
Version: 1.1
Summary: A library that facilitates a broad set of tools for analysing hidden activations of neural models.
Home-page: https://github.com/i-machine-think/diagnnose
License: Apache License 2.0
Keywords: interpretability,analysis,deep learning,nlp
Platform: UNKNOWN
Classifier: Intended Audience :: Science/Research
Classifier: Topic :: Scientific/Engineering :: Artificial Intelligence
Classifier: Programming Language :: Python :: 3.6
Requires-Python: >=3.6.0
Requires-Dist: torch (>=1.5.1)
Requires-Dist: torchtext (==0.6.0)
Requires-Dist: skorch (>=0.7.0)
Requires-Dist: transformers (>=4.0.0)
Requires-Dist: tqdm
Requires-Dist: dill
Requires-Dist: unidecode
Provides-Extra: dev
Requires-Dist: check-manifest ; extra == 'dev'
Provides-Extra: test
Requires-Dist: coverage ; extra == 'test'
